<annotation>
	<folder>annotations</folder>
	<filename>img_163.jpg</filename>
	<path>C:\Repos\HackOHIO-2021/poles/train/annotations/img_163.jpg</path>
	<source>
		<database>Unknown</database>
	</source>
	<size>
		<width>424</width>
		<height>982</height>
		<depth>3</depth>
	</size>
	<segmented>0</segmented>
	<object>
		<name>pole</name>
		<pose>Unspecified</pose>
		<truncated>0</truncated>
		<difficult>0</difficult>
		<bndbox>
			<xmin>72</xmin>
			<ymin>116</ymin>
			<xmax>312</xmax>
			<ymax>926</ymax>
		</bndbox>
	</object>
</annotation>