<annotation>
	<folder>annotations</folder>
	<filename>img_256.jpg</filename>
	<path>C:\Repos\HackOHIO-2021/poles/train/annotations/img_256.jpg</path>
	<source>
		<database>Unknown</database>
	</source>
	<size>
		<width>474</width>
		<height>708</height>
		<depth>3</depth>
	</size>
	<segmented>0</segmented>
	<object>
		<name>pole</name>
		<pose>Unspecified</pose>
		<truncated>1</truncated>
		<difficult>0</difficult>
		<bndbox>
			<xmin>200</xmin>
			<ymin>1</ymin>
			<xmax>305</xmax>
			<ymax>707</ymax>
		</bndbox>
	</object>
</annotation>